_c3.cpython-39-darwin.so
c3py.py
libc3.dylib
c3py-0.0.7.dist-info/LICENSE
c3py-0.0.7.dist-info/METADATA
c3py-0.0.7.dist-info/WHEEL
c3py-0.0.7.dist-info/top_level.txt
c3py-0.0.7.dist-info/RECORD
