Metadata-Version: 2.1
Name: c3py
Version: 0.0.7
Summary: Compressed Continuous Computation Library in Python
Home-page: https://github.com/goroda/compressed-continuous-computation
Author: Alex Gorodetsky
Author-email: alex@alexgorodetsky.com
License: UNKNOWN
Keywords: highd-approximation machine-learning uncertainty-quantification tensors
Platform: UNKNOWN
Classifier: Natural Language :: English
Classifier: Programming Language :: C
Classifier: Programming Language :: Python
Classifier: Programming Language :: Python :: 3 :: Only
Classifier: License :: OSI Approved :: BSD License
Classifier: Topic :: Scientific/Engineering :: Mathematics
License-File: LICENSE
Requires-Dist: numpy
Requires-Dist: pathlib
